[
    {
        "value": "passwords",
        "label": "Passwords"
    },
    {
        "value": "api_keys",
        "label": "API keys"
    },
    {
        "value": "encryption_keys",
        "label": "Encryption keys"
    },

    {
        "value": "certificates",
        "label": "Certificates"
    },
    {
        "value": "ssh_keys",
        "label": "SSH keys"
    },
    {
        "value": "database_credentials",
        "label": "Database credentials"
    },
    {
        "value": "oauth_tokens",
        "label": "Oauth tokens"
    },
    {
        "value": "tokens_and_secrets",
        "label": "Encryption keys"
    },
    {
        "value": "configuration_files",
        "label": "Configuration files"
    },
    {
        "value": "digital_certificates",
        "label": "Digital certificates"
    },
    {
        "value": "access_code",
        "label": "Access codes"
    },
    {
        "value": "license_keys",
        "label": "License keys"
    }
]
